torchCompactRadius/__init__.py
torchCompactRadius/compiler.py
torchCompactRadius/neighborhood.py
torchCompactRadius/setup.py
torchCompactRadius/util.py
torchCompactRadius/compactHashing/cellTable.py
torchCompactRadius/compactHashing/cppSearch.py
torchCompactRadius/compactHashing/cppWrapper.py
torchCompactRadius/compactHashing/datastructure.py
torchCompactRadius/compactHashing/hashTable.py
torchCompactRadius/cppSrc/common.h
torchCompactRadius/cppSrc/cppWrapper.cpp
torchCompactRadius/cppSrc/hashing.h
torchCompactRadius/cppSrc/hashing_cpu.cpp
torchCompactRadius/cppSrc/hashing_cuda.cu
torchCompactRadius/cppSrc/neighborhood.h
torchCompactRadius/cppSrc/neighborhoodDynamic.h
torchCompactRadius/cppSrc/neighborhoodDynamic_cpu.cpp
torchCompactRadius/cppSrc/neighborhoodDynamic_cuda.cu
torchCompactRadius/cppSrc/neighborhoodFixed.h
torchCompactRadius/cppSrc/neighborhoodFixed_cpu.cpp
torchCompactRadius/cppSrc/neighborhoodFixed_cuda.cu
torchCompactRadius/cppSrc/neighborhoodSmall.h
torchCompactRadius/cppSrc/neighborhoodSmall_cpu.cpp
torchCompactRadius/cppSrc/neighborhoodSmall_cuda.cu
torchCompactRadius/searchAlgorithms/compactSearch.py
torchCompactRadius/searchAlgorithms/pythonSearch.py
torchCompactRadius/searchAlgorithms/pythonSearchDynamic.py
torchCompactRadius/searchAlgorithms/pythonSearchFixed.py
torchCompactRadius/searchAlgorithms/radiusNaive.py
torchCompactRadius-0.2.4.dist-info/LICENSE
torchCompactRadius-0.2.4.dist-info/METADATA
torchCompactRadius-0.2.4.dist-info/WHEEL
torchCompactRadius-0.2.4.dist-info/top_level.txt
torchCompactRadius-0.2.4.dist-info/RECORD
