Metadata-Version: 2.2
Name: torchCompactRadius
Version: 0.2.4
Summary: Compact Hashing based radius search for pyTorch using C++/CUDA backends.
Author-email: Rene Winchenbach <contact@fluids.dev>
Maintainer-email: Rene Winchenbach <contact@fluids.dev>
License: MIT License
Project-URL: Repository, https://github.com/wi-re/torchCompactRadius
Project-URL: Issues, https://github.com/wi-re/torchCompactRadius/issues
Keywords: sph,radius,pytorch
Classifier: Development Status :: 4 - Beta
Classifier: Intended Audience :: Developers
Classifier: Programming Language :: Python :: 3
Classifier: License :: OSI Approved :: MIT License
Classifier: Operating System :: OS Independent
Requires-Python: >=3.10
License-File: LICENSE
Requires-Dist: torch
Requires-Dist: numpy
